MANIFEST.in
README.rst
setup.py
pimp/__init__.py
pimp.egg-info/PKG-INFO
pimp.egg-info/SOURCES.txt
pimp.egg-info/dependency_links.txt
pimp.egg-info/entry_points.txt
pimp.egg-info/requires.txt
pimp.egg-info/top_level.txt