Metadata-Version: 1.0
Name: pimp
Version: 0.3.1dev
Summary: pimp installs magic packages. Install rpm packages from PyPi. No refunds.
Home-page: http://github.com/mbr/pimp
Author: Marc Brinkmann
Author-email: git@marcbrinkmann.de
License: MIT
Platform: UNKNOWN
